scrapyio/__about__.py
scrapyio/__init__.py
scrapyio/cli.py
scrapyio/downloader.py
scrapyio/engines.py
scrapyio/exceptions.py
scrapyio/http.py
scrapyio/item_loaders.py
scrapyio/item_middlewares.py
scrapyio/items.py
scrapyio/logger.py
scrapyio/middlewares.py
scrapyio/py.typed
scrapyio/settings.py
scrapyio/spider.py
scrapyio/types.py
scrapyio/utils.py
scrapyio/templates/configuration_template.py
scrapyio/templates/spider_file_template.py
scrapyio-0.0.8.dist-info/METADATA
scrapyio-0.0.8.dist-info/WHEEL
scrapyio-0.0.8.dist-info/entry_points.txt
scrapyio-0.0.8.dist-info/licenses/LICENSE
scrapyio-0.0.8.dist-info/RECORD
