Metadata-Version: 2.1
Name: scrapyio
Version: 0.0.8
Project-URL: Documentation, https://github.com/karosis88/scrapyio#readme
Project-URL: Issues, https://github.com/karosis88/scrapyio/issues
Project-URL: Source, https://github.com/karosis88/scrapyio
Author-email: Karen Petrosyan <kar.petrosyanpy@gmail.com>
License-Expression: MIT
License-File: LICENSE
Classifier: Programming Language :: Python
Classifier: Programming Language :: Python :: 3.8
Classifier: Programming Language :: Python :: 3.9
Classifier: Programming Language :: Python :: 3.10
Classifier: Programming Language :: Python :: 3.11
Classifier: Programming Language :: Python :: Implementation :: CPython
Classifier: Programming Language :: Python :: Implementation :: PyPy
Requires-Python: >=3.7
Requires-Dist: click==8.1.3
Requires-Dist: httpx==0.23.3
Requires-Dist: pydantic==1.10.7
Provides-Extra: orjson
Requires-Dist: orjson==3.8.9; extra == 'orjson'
Provides-Extra: sqlite
Requires-Dist: aiosqlite==0.18.0; extra == 'sqlite'
Requires-Dist: sqlalchemy==2.0.8; extra == 'sqlite'
